slm_packager/__init__.py
slm_packager/api/__init__.py
slm_packager/api/server.py
slm_packager/cli/__init__.py
slm_packager/cli/main.py
slm_packager/config/__init__.py
slm_packager/config/loader.py
slm_packager/config/models.py
slm_packager/evaluation/__init__.py
slm_packager/evaluation/benchmark.py
slm_packager/quantization/__init__.py
slm_packager/quantization/binary_manager.py
slm_packager/quantization/quantizers.py
slm_packager/registry/__init__.py
slm_packager/registry/downloader.py
slm_packager/registry/models.json
slm_packager/runtime/__init__.py
slm_packager/runtime/base.py
slm_packager/runtime/llama_cpp.py
slm_packager/runtime/onnx.py
slm_packager/runtime/transformers.py
slm_packager-0.2.1.dist-info/licenses/LICENSE
slm_packager-0.2.1.dist-info/METADATA
slm_packager-0.2.1.dist-info/WHEEL
slm_packager-0.2.1.dist-info/entry_points.txt
slm_packager-0.2.1.dist-info/top_level.txt
slm_packager-0.2.1.dist-info/RECORD
