Metadata-Version: 2.4
Name: slm-packager
Version: 0.2.1
Summary: A unified runtime and developer layer for Small Language Models
Author: SLM Packager Team
License: Apache-2.0
Project-URL: Homepage, https://github.com/Ayo-Cyber/slm-packager
Project-URL: Documentation, https://github.com/Ayo-Cyber/slm-packager#readme
Project-URL: Repository, https://github.com/Ayo-Cyber/slm-packager
Project-URL: Issues, https://github.com/Ayo-Cyber/slm-packager/issues
Project-URL: Changelog, https://github.com/Ayo-Cyber/slm-packager/blob/main/CHANGELOG.md
Keywords: llm,small-language-models,gguf,transformers,onnx,ai,machine-learning,model-serving,inference
Classifier: Development Status :: 4 - Beta
Classifier: Intended Audience :: Developers
Classifier: Intended Audience :: Science/Research
Classifier: Programming Language :: Python :: 3
Classifier: Programming Language :: Python :: 3.9
Classifier: Programming Language :: Python :: 3.10
Classifier: Programming Language :: Python :: 3.11
Classifier: Topic :: Scientific/Engineering :: Artificial Intelligence
Classifier: Topic :: Software Development :: Libraries :: Python Modules
Classifier: Operating System :: OS Independent
Requires-Python: >=3.9
License-File: LICENSE
Requires-Dist: fastapi>=0.109.0
Requires-Dist: uvicorn>=0.27.0
Requires-Dist: click>=8.1.7
Requires-Dist: pydantic>=2.6.0
Requires-Dist: llama-cpp-python>=0.2.55
Requires-Dist: onnxruntime>=1.17.0
Requires-Dist: transformers>=4.37.0
Requires-Dist: torch>=2.2.0
Requires-Dist: pyyaml>=6.0.1
Requires-Dist: psutil>=5.9.0
Requires-Dist: accelerate>=0.25.0
Requires-Dist: huggingface-hub>=0.19.0
Provides-Extra: dev
Requires-Dist: pytest>=8.0.0; extra == "dev"
Requires-Dist: pytest-cov>=4.1.0; extra == "dev"
Requires-Dist: pytest-asyncio>=0.23.0; extra == "dev"
Requires-Dist: pytest-mock>=3.12.0; extra == "dev"
Requires-Dist: black>=24.0.0; extra == "dev"
Requires-Dist: isort>=5.13.0; extra == "dev"
Requires-Dist: mypy>=1.8.0; extra == "dev"
Requires-Dist: httpx>=0.26.0; extra == "dev"
Provides-Extra: onnx
Requires-Dist: onnxruntime-genai>=0.4.0; extra == "onnx"
Dynamic: license-file
